Metadata-Version: 2.1
Name: self_stats_app
Version: 0.1.0
Summary: Process Google Takeout data and visualize it using Dash.
Author: Colton Robbins
Author-email: coltonrobbins73@gmail.com
Requires-Dist: alabaster ==0.7.16
Requires-Dist: Babel ==2.14.0
Requires-Dist: blinker ==1.7.0
Requires-Dist: certifi ==2024.2.2
Requires-Dist: charset-normalizer ==3.3.2
Requires-Dist: click ==8.1.7
Requires-Dist: dash ==2.16.1
Requires-Dist: dash-bootstrap-components ==1.6.0
Requires-Dist: dash-core-components ==2.0.0
Requires-Dist: dash-html-components ==2.0.0
Requires-Dist: dash-table ==5.0.0
Requires-Dist: docutils ==0.20.1
Requires-Dist: Flask ==3.0.3
Requires-Dist: idna ==3.7
Requires-Dist: imagesize ==1.4.1
Requires-Dist: importlib-metadata ==7.1.0
Requires-Dist: itsdangerous ==2.2.0
Requires-Dist: Jinja2 ==3.1.3
Requires-Dist: MarkupSafe ==2.1.5
Requires-Dist: mypy-extensions ==1.0.0
Requires-Dist: nest-asyncio ==1.6.0
Requires-Dist: numpy ==1.26.4
Requires-Dist: packaging ==24.0
Requires-Dist: pandas ==2.2.2
Requires-Dist: pathspec ==0.12.1
Requires-Dist: platformdirs ==4.2.0
Requires-Dist: plotly ==5.21.0
Requires-Dist: Pygments ==2.17.2
Requires-Dist: python-dateutil ==2.9.0.post0
Requires-Dist: pytz ==2024.1
Requires-Dist: regex ==2024.4.16
Requires-Dist: retrying ==1.3.4
Requires-Dist: ruptures ==1.1.9
Requires-Dist: scipy ==1.13.0
Requires-Dist: six ==1.16.0
Requires-Dist: snowballstemmer ==2.2.0
Requires-Dist: soupsieve ==2.5
Requires-Dist: Sphinx ==7.2.6
Requires-Dist: sphinxcontrib-applehelp ==1.0.8
Requires-Dist: sphinxcontrib-devhelp ==1.0.6
Requires-Dist: sphinxcontrib-htmlhelp ==2.0.5
Requires-Dist: sphinxcontrib-jsmath ==1.0.1
Requires-Dist: sphinxcontrib-qthelp ==1.0.7
Requires-Dist: sphinxcontrib-serializinghtml ==1.1.10
Requires-Dist: tenacity ==8.2.3
Requires-Dist: tomli ==2.0.1
Requires-Dist: typing-extensions ==4.11.0
Requires-Dist: tzdata ==2024.1
Requires-Dist: tzlocal ==5.2
Requires-Dist: urllib3 ==2.2.1
Requires-Dist: webencodings ==0.5.1
Requires-Dist: Werkzeug ==3.0.2
Requires-Dist: zipp ==3.18.1
